{
 "于禁": [
  "與毛玠一同被曹操任命為水軍都督。",
  "在曹操水寨聽到擂鼓吶喊後，慌忙飛報曹操。",
  "因怕南軍搶入水寨，已差弓弩手在寨前放箭。"
 ],
 "周瑜": [
  "派魯肅去探聽諸葛亮是否知曉其計謀。",
  "得知諸葛亮已識破計謀後，決定殺死諸葛亮。",
  "以軍中缺箭為由，要求諸葛亮三日內監造十萬枝箭。",
  "與諸葛亮立下軍令狀，並暗中吩咐軍匠故意遲延、不備齊物件以陷害諸葛亮。",
  "與諸葛亮暗中寫下「火」字，決定採用火攻計策。",
  "接受蔡中、蔡和詐降，並密令甘寧將計就計以通報消息。",
  "在帳下大會諸將時，因黃蓋反對長期對峙而大怒，下令斬殺黃蓋。",
  "在眾官求情下免黃蓋死罪，但下令將黃蓋拖翻打五十脊杖，實施苦肉計。",
  "向魯肅透露痛打黃蓋是苦肉計，目的是瞞過曹操以便行火攻。"
 ],
 "張遼": [
  "被曹操差人從旱寨喚去，帶弓弩軍三千火速到江邊助射。"
 ],
 "徐晃": [
  "被曹操差人從旱寨喚去，帶弓弩軍三千火速到江邊助射。"
 ],
 "曹操": [
  "在重霧迷江時，判斷江上必有埋伏，下令不可輕動。",
  "撥水軍弓弩手向江中亂箭射擊。",
  "差人往旱寨喚張遼、徐晃帶弓弩軍助射。",
  "得知南軍船輕水急已遠去後，懊悔不已。",
  "因折損十五六萬箭而心中氣悶。",
  "采纳荀攸計策，厚賞蔡中、蔡和，差二人去東吳詐降為奸細。"
 ],
 "甘寧": [
  "被周瑜密令殷勤接待蔡中、蔡和，並提防其通報消息。",
  "在黃蓋被斬時進前告求，希望周瑜寬恕黃蓋。",
  "被周瑜喝斥並亂棒打出。"
 ],
 "荀攸": [
  "向曹操進計，建議差人至東吳詐降為奸細內應。",
  "推薦蔡瑁的族弟蔡中、蔡和執行詐降任務。"
 ],
 "蔣幹": [
  "被諸葛亮指出周瑜的計謀是專門用來弄蔣幹的。"
 ],
 "諸葛亮": [
  "向魯肅指出周瑜的計謀是弄蔣幹，並預言蔡、張兩人必死。",
  "囑咐魯肅在周瑜面前勿言自己先知此事。",
  "接受周瑜三日造十萬箭的任務，並立下軍令狀。",
  "向魯肅借二十隻船、軍士、布幔和草束，並囑咐魯肅保密。",
  "在第三日四更時分，請魯肅同往取箭。",
  "命船隻頭西尾東擺開，在曹操水寨前擂鼓吶喊。",
  "料定曹操在重霧中不敢出兵，只敢放箭。",
  "命船隻弔回，頭東尾西逼近水寨受箭，並繼續擂鼓吶喊。",
  "令軍士齊聲叫謝丞相箭，隨後乘船急回。",
  "向魯肅解釋自己三日前已算定今日有大霧。",
  "將十餘萬枝箭搬入中軍帳交納。",
  "與周瑜暗中寫下「火」字，確認火攻計策。",
  "指出周瑜接受蔡中、蔡和詐降是將計就計。",
  "袖手旁觀黃蓋受刑，並笑魯肅不知這是苦肉計。",
  "囑咐魯肅見周瑜時切勿言自己先知其事，只說埋怨都督。"
 ],
 "闞澤": [
  "聞訊前來問候受刑的黃蓋。",
  "觀察周瑜舉動，料出黃蓋受責是苦肉計。",
  "被黃蓋以心腹相告，欣然領諾獻詐降書。"
 ],
 "魯肅": [
  "領周瑜言語去舟中探聽諸葛亮。",
  "聽諸葛亮說破計謀後失色，支吾半晌後別孔明而回。",
  "將諸葛亮先知之事實報告周瑜。",
  "勸周瑜不要殺諸葛亮，以免被曹操笑話。",
  "私自撥給諸葛亮二十隻船、軍士及布幔束草等物。",
  "不提起借船之事，只言諸葛亮不用箭竹等物自有道理。",
  "在船上驚問諸葛亮若曹兵齊出如何應對。",
  "驚嘆諸葛亮神機妙算，並問其何以知今日大霧。",
  "入見周瑜，備說諸葛亮取箭之事。",
  "指出蔡中、蔡和之降多應是詐，不可收用。",
  "被周瑜叱責後默然退下，並往告諸葛亮。",
  "問諸葛亮為何袖手旁觀不發一語。",
  "聽諸葛亮解釋後方悟這是苦肉計。",
  "入帳見周瑜，詢問為何痛責黃蓋。",
  "向周瑜報告諸葛亮也埋怨都督情薄。"
 ],
 "黃蓋": [
  "潛入中軍見周瑜，建議使用火攻。",
  "表示願行詐降計，雖肝腦塗地亦無怨悔。",
  "在大會諸將時反對長期對峙，主張速戰或投降。",
  "因言降被周瑜大怒，喝令斬首。",
  "怒斥周瑜，並被甘寧求情後遭亂棒打出。",
  "被拖翻在地，打了五十脊杖，皮開肉綻。",
  "扶歸本寨後昏絕幾次，動問之人無不下淚。",
  "臥於帳中，諸將來問時不言語，但長吁而已。",
  "向闞澤表明受吳侯三世厚恩，無以為報，故獻苦肉計。",
  "遍觀軍中無可為心腹者，惟信闞澤有忠義之心。",
  "向闞澤表明獻詐降書之意。"
 ]
}