{
 "劉備": [
  "攀住曹操欲殺張遼的手臂，並請關羽以性命担保張遼的忠義。",
  "向漢獻帝自陳身世，被確認為漢室叔父。",
  "被漢獻帝拜為左將軍宜城亭侯。",
  "在許田打圍時射中一隻兔子，並向曹操稱賀以掩護關羽。",
  "阻止關羽在許田打圍時斬殺曹操，指出曹操身側有天子保護。",
  "勸告關羽暫時隱忍，不可輕言討伐曹操。"
 ],
 "呂布": [
  "已死（僅被臧霸聞知提及，無本回行動）。"
 ],
 "孔融": [
  "因諫阻曹操因袁術親戚關係定罪楊彪，與曹操爭辯。",
  "引用周公典故諷刺曹操，迫使曹操免去楊彪官職。"
 ],
 "張遼": [
  "欲被曹操殺害時被劉備和關羽求情。",
  "被曹操釋放並解衣賜之，隨後投降曹操。",
  "被曹操拜為中郎將，賜爵關內侯，並受命招安臧霸。"
 ],
 "曹操": [
  "舉劍欲殺張遼，後因劉備求情而釋放張遼並收為部下。",
  "封臧霸為瑯琊相，孫觀等人加官，令其守青、徐沿海地面。",
  "將呂布妻女載回許都，大犒三軍後班師回許昌。",
  "表奏劉備軍功，引劉備見漢獻帝。",
  "密使人誣告楊彪交通袁術，將楊彪下獄。",
  "因孔融諫言，不得已免去楊彪官職。",
  "因議郎趙彥上疏劾其專橫，將其收捕殺害。",
  "聽從程昱建議，請漢獻帝田獵以觀動靜。",
  "在許田打圍時，借天子寶雕弓射中大鹿，群臣呼萬歲時遮於天子之前迎受。",
  "不還天子寶雕弓，親自懸帶。",
  "察覺董承受賜錦袍玉帶可疑，強行查看並試穿。",
  "懷疑董承衣帶中有謀，但最終未奪回賜物。"
 ],
 "漢獻帝": [
  "檢閱宗族世譜，確認劉備為其叔父。",
  "拜劉備為左將軍宜城亭侯，並設宴款待。",
  "因曹操弄權而憂慮，向伏皇后表達對曹操專橫的恐懼。",
  "採納伏完計策，咬破指尖以血寫密詔，縫於玉帶紫錦襯內。",
  "宣董承入宮，賜予錦袍玉帶，並密語董承細觀。",
  "在許田打圍時連射三箭不中大鹿，命曹操代射。",
  "回宮後向伏皇后哭訴曹操無禮及必有異謀。"
 ],
 "程昱": [
  "勸曹操趁威名日盛之際行王霸之事。",
  "建議曹操請天子田獵，以觀朝臣動靜。"
 ],
 "荀彧": [
  "入見曹操，表示天子認劉備為叔恐無益於曹操。"
 ],
 "董卓": [
  "已死（僅被漢獻帝回憶提及，無本回行動）。"
 ],
 "董承": [
  "被漢獻帝宣入內閣，賜予錦袍玉帶及密詔。",
  "辭別漢獻帝後，發現玉帶襯內燒破處露出血字密詔。",
  "讀密詔後涕淚交流，一夜未眠，沈思滅操之計。",
  "與王子服結盟，共同書立義狀，誓殺曹賊。",
  "邀請種輯、吳碩加入密謀，二人讀詔後同意書名。",
  "與吳子蘭、王子服、種輯、吳碩五人會飲並書名。",
  "推病不接見馬騰，後被馬騰識破並責罵。",
  "向馬騰展示密詔，馬騰讀後同意統西涼兵為外應並書名。",
  "與馬騰等人歃血為盟，並檢閱《鴛行鷺序簿》尋找劉氏宗族成員。"
 ],
 "袁術": [
  "已死（僅被臧霸聞知提及，無本回行動）。"
 ],
 "關羽": [
  "跪求曹操留下張遼，並以性命担保。",
  "在許田打圍時見曹操遮於天子之前迎受群臣呼賀，大怒欲斬曹操。",
  "被劉備搖手送目制止，不敢動。",
  "事後問劉備為何阻止他殺曹操，並表示後必為禍。"
 ],
 "馬騰": [
  "入覲將還，來見董承卻被推病拒之。",
  "因被拒而大怒，指責滿朝非救國之人。",
  "被董承挽留並展示密詔後，同意統西涼兵為外應並書名。",
  "建議從劉氏宗族中尋找共議之人。"
 ]
}