{
 "劉禪": [
  "因諸葛亮欲親征南蠻，擔憂東吳孫權與北魏曹丕趁虛來攻，向諸葛亮表達疑慮。",
  "批准諸葛亮自領大軍征討南蠻的請求，並表示年幼無知，唯聽相父斟酌行事。"
 ],
 "孟獲": [
  "聽知諸葛亮攻破雍闓等人後，聚齊三洞元帥商議分兵三路迎敵。",
  "在與王平軍對陣時，因陣勢混亂而輕視諸葛亮，並派忙牙長出戰。",
  "追擊王平與關索時，遭張嶷、張翼截斷歸路，夾攻之下大敗，引部將死戰得脫。",
  "逃至錦帶山時，被趙雲攔住去路，棄馬爬山越嶺後，被魏延伏兵生擒。",
  "被解至蜀軍大寨後，以兩川土地非蜀主所有為由反駁諸葛亮的責問，並堅稱不服。",
  "要求諸葛亮放其回去再戰，承諾若再被擒方肯歸服，隨後被釋放。"
 ],
 "孫權": [
  "與蜀國講和，諸葛亮認為其無異心，故未將其視為當前主要威脅。"
 ],
 "張苞": [
  "被諸葛亮留下作為救應之軍，護衛成都，未參與此次南征行動。"
 ],
 "曹丕": [
  "新近戰敗，銳氣已喪，諸葛亮認為其未能遠圖，故未擔憂其來攻。"
 ],
 "李嚴": [
  "駐守白帝城，諸葛亮認為此人可抵擋東吳陸遜的進攻。"
 ],
 "王平": [
  "被諸葛亮任命為副將，並受命率軍前往左路迎敵。",
  "在左路與魏延、張嶷等軍夾攻董荼那寨，導致蠻兵大敗。",
  "在與孟獲軍對陣時詐敗，誘使孟獲深入，隨後復兵殺回參與夾攻。"
 ],
 "諸葛亮": [
  "因蠻王孟獲犯境侵掠，入朝奏請後主，自領五十萬大軍征討南蠻。",
  "採用反間計，故意放還雍闓與高定的部下以製造兩方猜忌。",
  "識破高定詐降，利用朱褒的密書激高定殺死雍闓，隨後任命高定為益州太守。",
  "重用永昌太守呂凱，任命其為行軍敎授兼鄉導官，並採用其「平蠻指掌圖」。",
  "任命馬謖為參軍，採納其「攻心為上，攻城為下」的建議。",
  "故意不用趙雲、魏延，而以王平、馬忠、張嶷、張翼等將領分路迎敵，實則暗中部署計策。",
  "利用趙雲、魏延的銳氣，令其深入敵境擊殺金環三結，並伏兵擒獲董荼那、阿會喃。",
  "設計誘使孟獲陷入重圍，最終由魏延將其生擒。",
  "將俘虜的蠻兵全部釋放以安其心，並釋放孟獲，要求再戰以服其心。"
 ],
 "趙雲": [
  "被任命為大將總督軍馬，但因諸葛亮擔心其涉險而未在初期被派往前線迎敵。",
  "與魏延私自探路，生擒蠻兵並獲知敵軍寨位後，率兵夜襲金環三結大寨。",
  "在戰鬥中一槍刺死金環三結元帥並梟其首級，隨後分兵抄襲阿會喃寨。",
  "在錦帶山攔截孟獲，衝殺一陣後生擒無數蠻兵。"
 ],
 "關羽": [
  "已故，其子關索投奔蜀軍，諸葛亮令關索為前部先鋒。"
 ],
 "關興": [
  "被諸葛亮留下作為救應之軍，護衛成都，未參與此次南征行動。"
 ],
 "陸遜": [
  "駐守東吳，諸葛亮認為李嚴可抵擋陸遜，故不擔憂東吳來攻。"
 ],
 "馬謖": [
  "因兄長馬良新亡而掛孝，奉天子詔命賜酒帛給蜀軍。",
  "向諸葛亮提出「攻心為上，攻城為下」的用兵之道，深受諸葛亮讚賞。",
  "被諸葛亮任命為參軍，統率大兵前進。"
 ],
 "馬超": [
  "守把漢中諸處關口，諸葛亮認為不必擔憂曹丕遠圖。"
 ],
 "魏延": [
  "被任命為大將總督軍馬，初期與張翼、王平一同迎敵並生擒鄂煥。",
  "因諸葛亮不用其為前線主將而心生慍色，與趙雲私自探路並擊殺金環三結。",
  "分兵抄襲董荼那寨，與王平夾攻導致蠻兵大敗。",
  "受諸葛亮計策，在錦帶山谷伏兵，最終生擒孟獲。"
 ]
}