{
 "于禁": [
  "被曹操任命為先鋒。"
 ],
 "劉備": [
  "已被曹操擊敗並趕出許都。"
 ],
 "劉表": [
  "因禰衡戲謔而將其遣往江夏見黃祖。",
  "聽從韓嵩建議派其前往許都觀察動靜。",
  "因韓嵩回許都後勸其歸順曹操而大怒欲斬之，後赦免。",
  "聞知禰衡被黃祖斬殺後嗟呀不已，並將其葬於鸚鵡洲邊。"
 ],
 "吉平": [
  "受董承之託，以醫治頭風為名，企圖在藥中下毒殺害曹操。",
  "下毒之事敗露後，被曹操下令拷問。",
  "遭受酷刑後仍堅不吐實，並痛罵曹操。",
  "為求速死以全名節，假意供招，隨後撞階而死。",
  "死後被曹操下令分其肢體號令。"
 ],
 "呂蒙": [
  "本回未登場，僅在曹操列举人才時被提及。"
 ],
 "夏侯惇": [
  "被曹操稱為天下奇才。",
  "被禰衡諷刺稱為「完體將軍」。"
 ],
 "孔融": [
  "諫阻曹操斬殺劉岱、王忠。",
  "建議曹操待來春再圖徐州，並先招安張繡、劉表。",
  "向漢獻帝上表推薦禰衡。",
  "在曹操宴會上為禰衡求情，稱其罪同胥靡，不足發明王之夢。"
 ],
 "張繡": [
  "當面撕碎袁紹的招安書並叱退來使。",
  "聽從賈詡建議，前往許都投降曹操。",
  "被曹操封為揚武將軍。",
  "受曹操命令寫信招安劉表。"
 ],
 "張遼": [
  "在曹操宴會上因禰衡出言不遜而掣劍欲斬之。",
  "被禰衡諷刺為可使擊鼓鳴金之人。"
 ],
 "徐晃": [
  "被曹操任命為先鋒。",
  "被禰衡諷刺為可使屠豬殺狗之人。"
 ],
 "曹仁": [
  "被曹操稱為世間福將。",
  "被禰衡諷刺呼為「要錢太守」。"
 ],
 "曹操": [
  "免劉岱、王忠死罪，將其黜罷爵祿。",
  "派遣劉曄前往招安張繡。",
  "接受張繡投降，並封其為揚武將軍，封賈詡為執金吾使。",
  "命張繡寫信招安劉表。",
  "召見禰衡，因不滿其傲慢而令其充任鼓吏以辱之。",
  "派遣禰衡前往荊州出使劉表。",
  "聽從荀彧建議，決定先滅袁紹、後滅劉備。",
  "因董承染病，派太醫吉平前去醫治。",
  "收留告密的秦慶童，並將其藏匿於府中。",
  "詐患頭風召吉平用藥，故意遲延以試探吉平。",
  "發現吉平下毒後，將其逮捕並嚴刑拷問。",
  "在宴會上公開吉平謀反之事，並擒獲王子服等四人。",
  "搜出董承家中的衣帶詔和義狀。",
  "決定廢獻帝，更立新君。"
 ],
 "李典": [
  "被曹操任命為先鋒。",
  "被禰衡諷刺為可使傳書送檄之人。"
 ],
 "楊修": [
  "本回未登場，僅在禰衡提及許都人物時被提及。"
 ],
 "樂進": [
  "被曹操任命為先鋒。",
  "被禰衡諷刺為可使取狀讀招之人。"
 ],
 "滿寵": [
  "被曹操任命為從事。",
  "被禰衡諷刺為可使飲酒食糟之人。"
 ],
 "漢獻帝": [
  "閱讀孔融推薦禰衡的奏表，並將其轉付曹操。",
  "得知董承染病，派太醫吉平前去醫治。"
 ],
 "禰衡": [
  "被孔融推薦給漢獻帝。",
  "當面辱罵曹操手下眾將，稱其為衣架、飯囊等。",
  "被曹操任命為鼓吏。",
  "在宴會上擊鼓為《漁陽三撾》，並裸體而立以顯清白。",
  "痛罵曹操為眼濁、口濁、耳濁、身濁、腹濁、心濁。",
  "被曹操派遣前往荊州出使劉表。",
  "在荊州雖頌德劉表但實為譏諷，被劉表遣往江夏。",
  "在江夏被黃祖斬殺，至死罵不絕口。",
  "被劉表葬於鸚鵡洲邊。"
 ],
 "程昱": [
  "被曹操稱為機深智遠，雖蕭何、陳平不及。",
  "被禰衡諷刺為可使關門閉戶之人。"
 ],
 "荀彧": [
  "建議曹操先滅袁紹、後滅劉備。",
  "在曹操宴會上制止眾人殺害禰衡。",
  "對曹操不問禰衡下落表示疑惑。",
  "在曹操宴會上提醒眾人不可起身迎接禰衡。"
 ],
 "荀攸": [
  "建議孔融擔任出使荊州說服劉表的人選。",
  "向孔融傳達曹操欲求有文名之士的意圖。"
 ],
 "董承": [
  "日夜與王子服等人商議對付曹操之計。",
  "因感憤曹操驕橫而染病。",
  "在夢中與王子服等人商議圍殺曹操，醒後被吉平察覺。",
  "與吉平咬指為誓，並出示衣帶詔。",
  "因家奴秦慶童與侍妾私通而懲罰秦慶童。",
  "因憂國事而託病不赴曹操宴會。",
  "被曹操擒獲並監禁全家。"
 ],
 "袁紹": [
  "派遣使者招安張繡，被張繡撕書叱退。",
  "再次派遣使者至荊州，被劉表問計。"
 ],
 "許褚": [
  "被曹操稱為勇不可當。",
  "被禰衡諷刺為可使牧牛放馬之人。"
 ],
 "賈詡": [
  "留劉曄於家中，並分析從曹操的三點好處。",
  "隨張繡前往許都投降。",
  "被曹操封為執金吾使。",
  "建議曹操派有文名之士去說服劉表。"
 ],
 "郭嘉": [
  "被曹操稱為機深智遠，雖蕭何、陳平不及。",
  "被禰衡諷刺為可使白詞念賦之人。"
 ],
 "韓遂": [
  "本回未登場，僅在董承夢中提及馬騰結連韓遂起兵。"
 ],
 "馬騰": [
  "本回未登場，僅在董承夢中提及馬騰結連韓遂起兵。"
 ],
 "黃祖": [
  "與禰衡共飲時因禰衡侮辱而將其斬殺。"
 ]
}