{
 "劉備": [
  "劉備聞知曹丕自立為大魏皇帝且傳言漢帝已遇害，痛哭終日並下令百官挂孝設祭。",
  "劉備因憂慮而染成疾病，將政務託付給諸葛亮。",
  "劉備拒絕諸葛亮及眾官尊其為帝的建議，認為這與篡竊無異。",
  "劉備親至諸葛亮臥榻前詢問病情，諸葛亮假裝病重不語以逼迫劉備。",
  "劉備最終同意諸葛亮建議，築臺於成都武擔之南並登壇祭告受皇帝璽綬。",
  "劉備改元章武元年，立吳氏為皇后，立劉禪為太子。",
  "劉備在設朝時降詔欲起兵攻伐東吳以報關羽被殺之仇。"
 ],
 "劉禪": [
  "劉備立劉禪為太子。"
 ],
 "司馬懿": [
  "司馬懿諫阻曹丕立即接受漢帝禪位詔書，建議先上表謙辭以絕天下之謗。",
  "後人觀受禪臺有詩歎曰：「黃初欲學唐虞事，司馬將來作樣看。」"
 ],
 "孫權": [
  "劉備降詔稱關羽被東吳孫權所害，欲起兵攻伐東吳。"
 ],
 "曹丕": [
  "曹丕接受漢帝禪位詔書後，因司馬懿建議而先上表謙辭。",
  "曹丕命張音持節奉璽至魏王宮，並令華歆令漢帝築受禪臺。",
  "曹丕登受禪臺受八般大禮，登上帝位，改延康元年為黃初元年，國號大魏。",
  "曹丕傳旨大赦天下，諡父曹操為太祖武皇帝。",
  "曹丕封華歆為司徒，王朗為司空。",
  "曹丕因疑許昌宮室多妖，自許昌幸洛陽，大建宮室。",
  "曹丕在受禪時驚倒於臺上，數日不能設朝。"
 ],
 "曹操": [
  "曹丕諡父曹操為太祖武皇帝。"
 ],
 "曹洪": [
  "曹洪帶劍入殿力請獻帝出殿。",
  "曹洪索要玉璽，並喝令武士推出斬殺拒交的符寶郎祖弼。"
 ],
 "漢獻帝": [
  "漢獻帝聞華歆奏請禪位，大哭並拒絕棄祖宗基業。",
  "漢獻帝被曹洪、曹休逼迫，不得已出前殿。",
  "漢獻帝願將天下禪於魏王，令陳羣草禪國之詔，令華歆齎捧詔璽獻納。",
  "漢獻帝覽曹丕謙辭表，心甚驚疑。",
  "漢獻帝從華歆建議，卜地於繁陽築起三層高臺，擇日禪讓。",
  "漢獻帝親捧玉璽奉曹丕，受禪後被曹丕封為山陽公並即日便行。",
  "漢獻帝含淚拜謝曹丕，上馬而去，非宣召不許入朝。"
 ],
 "王朗": [
  "王朗奏稱漢室氣數已盡，宜早退避。",
  "王朗以目視華歆，暗示其行動。",
  "曹丕令王朗作表，自稱德薄，請別求大賢以嗣天位。",
  "曹丕封王朗為司空。"
 ],
 "華歆": [
  "華歆奏請漢帝效堯舜之道，以山川社稷禪與魏王。",
  "華歆引李伏、許芝近前奏稱祥瑞圖讖顯示魏當代漢。",
  "華歆厲聲威脅漢帝，稱若非魏王在朝弒帝者何止一人。",
  "華歆扯住龍袍，變色逼問漢帝許與不許。",
  "華歆建議漢帝再降詔，稱魏王自當允從。",
  "華歆建議漢帝築受禪臺，聚集公卿庶民明白禪位。",
  "華歆按劍指漢帝，厲聲言立一帝廢一帝是古之常道，並令漢帝即日便行。",
  "曹丕封華歆為司徒。"
 ],
 "諸葛亮": [
  "諸葛亮與許靖、譙周商議，言天下不可一日無君，欲尊漢中王為帝。",
  "諸葛亮引大小官僚上表，請漢中王卽皇帝位。",
  "諸葛亮苦勸漢中王繼統以延漢祀，並設計假裝病重以逼迫漢中王。",
  "諸葛亮揭穿計謀，讓外面文武衆官入見，漢中王見狀同意。",
  "諸葛亮率衆官恭上玉璽，並奏稱漢中王宜卽正位。",
  "諸葛亮封為丞相。"
 ],
 "譙周": [
  "譙周向諸葛亮及許靖指出成都西北角有黃氣沖霄、帝星見於畢胃昴之分，應漢中王當卽帝位。",
  "譙周在壇上高聲朗讀祭文，告祭皇天后土。"
 ],
 "賈詡": [
  "賈詡建議漢帝急降詔以安衆心。",
  "賈詡建議曹丕令華歆令漢帝築受禪臺，以釋羣疑而絕衆議。",
  "賈詡引大小官僚朝於臺下。"
 ],
 "趙雲": [
  "趙雲拜伏於階下，諫阻劉備起兵攻伐東吳。"
 ],
 "關羽": [
  "劉備降詔稱關羽被東吳孫權所害。"
 ]
}