{
 "劉備": [
  "聞關公父子遇害，哭倒於地，三日水漿不進，只是痛哭。",
  "誓與東吳誓不同日月，欲提兵問罪於吳以雪恨。",
  "聽從孔明勸諫，按兵不動，先與關公發喪。",
  "傳旨川中大小將士盡皆挂孝，親出南門招魂祭奠。"
 ],
 "司馬懿": [
  "建議曹操封孫權為驃騎將軍南昌侯，令其拒劉備。",
  "被曹操召至臥榻前，受託輔佐曹丕。"
 ],
 "吉平": [
  "被曹操提及與華佗案相比，作為華佗被下獄的藉口之一。"
 ],
 "周泰": [
  "被曹操提及，作為華佗的同鄉或相關人物被華歆介紹。"
 ],
 "夏侯惇": [
  "被曹操急召商議病情，至殿門前見伏皇后等鬼魂，驚倒得病。"
 ],
 "孫權": [
  "遣使上書曹操，稱天命已歸漢王，願率群下納土歸降。",
  "被曹操表封為驃騎將軍南昌侯，領荊州牧。"
 ],
 "曹丕": [
  "聞父喪，放聲痛哭，率官員出城十里迎櫬入城。",
  "受華歆持漢帝詔命，即日登位，受大小官僚拜舞起居。"
 ],
 "曹操": [
  "葬關公後每夜合眼便見關公，驚懼不已。",
  "欲起建始殿，親領人馬砍伐躍龍祠大梨樹，被樹神驚嚇致病。",
  "召華佗診治頭風，因疑華佗欲加害而將其下獄拷問。",
  "自殺華佗後病勢愈重，憂慮吳蜀之事。",
  "接受孫權歸降之書，大笑並封孫權官爵。",
  "夢三馬同槽，問賈詡吉凶，詡解為吉兆。",
  "見伏皇后、董貴人等鬼魂索命，驚倒遷於別宮養病。",
  "召夏侯惇商議，夏侯惇驚倒得病。",
  "召曹洪、陳羣、賈詡、司馬懿等囑以後事，立曹丕為嗣。",
  "遺命諸妾勤習女工，設祭於銅雀臺，設立疑塚七十二。",
  "氣絕而死，壽六十六歲，時建安二十五年春正月。"
 ],
 "曹植": [
  "被曹操評為虛華少誠實，嗜酒放縱，因此不被立為嗣。"
 ],
 "曹洪": [
  "領受曹操囑託，涕泣領命而出。",
  "參與曹操囑以後事之會議。"
 ],
 "漢獻帝": [
  "受華歆威逼，下詔封曹丕為魏王、丞相、冀州牧。"
 ],
 "華佗": [
  "被曹操召入診脈，診斷頭風病根在腦袋中，建議用利斧砍開腦袋取出風涎。",
  "被曹操疑為要殺害而拏下獄中拷問。",
  "感吳押獄厚意，修書令其取《青囊書》贈之。",
  "將《青囊書》贈與吳押獄後，旬日之後死於獄中。"
 ],
 "華歆": [
  "入奏曹操，推薦神醫華佗。",
  "自許昌飛馬至鄴郡，持漢帝詔命威逼百官，助曹丕嗣位。"
 ],
 "董承": [
  "作為鬼魂出現在曹操和夏侯惇面前索命。"
 ],
 "諸葛亮": [
  "勸劉備保養尊體，徐圖報仇，並分析東吳嫁禍曹操之計。",
  "諫止劉備立即伐吳，建議按兵不動，待吳魏不和時再伐。"
 ],
 "賈詡": [
  "建議曹操召洛陽良工蘇越畫建始殿圖像。",
  "諫止曹操廢棄華佗，稱其為世罕其匹之良醫。",
  "解讀曹操三馬同槽之夢為祿馬吉兆，使曹操不疑。"
 ],
 "關羽": [
  "被東吳獻首級給曹操，曹操以王侯禮祭葬之。"
 ],
 "關興": [
  "聞父遇害，號慟而來見劉備。"
 ],
 "陳登": [
  "曾被華佗醫治飲食不下之病，吐蛇一條而愈。",
  "曾被華佗預言三年後必復發而死，後果三年而死。"
 ],
 "馬騰": [
  "被曹操提及已死，曾疑其父子為禍。"
 ]
}