{
 "丁奉": [
  "被吳主孫休任命為主帥，率兵五萬前往救援蜀漢。",
  "分撥丁封、孫異引兵二萬向沔中而進，自率兵三萬向壽春而進，分兵三路來援。"
 ],
 "劉禪": [
  "聞知鄧艾兵至，慌召黃皓詢問情況。",
  "聽信黃皓詐傳之語，並宣師婆問事。",
  "接郤正建議，連發三詔召諸葛瞻入殿商議退兵之策。",
  "向諸葛瞻泣訴成都危矣，請求其救朕之命。",
  "撥成都兵將七萬給諸葛瞻。"
 ],
 "司馬昭": [
  "鄧艾修密書馳報司馬昭，報告其乘虛取成都之事。"
 ],
 "姜維": [
  "聞魏兵入境，引二萬兵守住劍閣。",
  "安慰董厥，表示若有自己在，必不容魏來吞蜀，並建議徐圖退敵之計。",
  "因諸葛緒領兵殺至關下而大怒，急引五千兵殺下關，直撞入魏陣中殺退諸葛緒。",
  "收兵回關。"
 ],
 "廖化": [
  "與姜維、張翼一同出現在劍閣關前，被董厥接入關上。"
 ],
 "諸葛亮": [
  "其子諸葛瞻在綿竹戰陣中放置木刻孔明遺像於四輪車上，嚇退師纂、鄧忠。"
 ],
 "鄧艾": [
  "因鍾會欲斬諸葛緒而大怒，但聽從子鄧忠勸告暫時容忍。",
  "見鍾會軍容甚肅心中不安，以言挑之並提出取成都之計，實則被鍾會視為庸才。",
  "暗中決定引兵從陰平小路進兵取成都，離劍閣七百里下寨。",
  "修密書遣使馳報司馬昭，並聚諸將問誰肯從其取成都，諸將願遵軍令。",
  "令子鄧忠引五千精兵鑿山開路，選兵三萬各帶乾糧繩索進發。",
  "行七百餘里至摩天嶺，見鄧忠與壯士哭泣，以「不入虎穴焉得虎子」激勵軍心。",
  "取氈自裹其身，先滾下摩天嶺，其餘軍士亦攀木挂樹而過。",
  "見道傍石碣上刻有諸葛武侯預言其越此之文，觀訖大驚並對碣再拜。",
  "見武侯舊寨空虛，嘆劉禪廢守險之兵，並對眾人说有來路無歸路，須併力攻江油。",
  "步行引二千餘人，星夜倍道來搶江油城。",
  "接受江油守將馬邈投降，用馬邈為鄉導官，並厚禮葬其自縊之妻。",
  "接陰平小路諸軍到江油取齊，逕來攻涪城。",
  "怒斬建議休養數日的部將田續，自驅兵至涪城，城中官吏軍民盡皆出降。",
  "得馬邈獻地理圖，驚懼蜀人據住前山，速喚師纂、鄧忠分付星夜逕去綿竹拒蜀兵。",
  "責問不戰而退的師纂、鄧忠，雖經苦勸方息怒，並令人哨探得知是諸葛瞻領兵。",
  "警告師纂、鄧忠再不取勝必當斬首，二人再戰被諸葛瞻殺退。",
  "聽監軍丘本建議，作書誘降諸葛瞻，被諸葛瞻扯碎並斬來使。",
  "大怒欲出戰，聽丘本諫言用奇兵，令王頎、牽弘伏兩軍於後，自引兵而來。",
  "諸葛瞻殺入魏陣，鄧艾敗走，隨後伏兵殺出，蜀兵大敗退入綿竹。",
  "令魏兵將綿竹圍得鐵桶相似。",
  "諸葛瞻中箭落馬自刎，其子諸葛尚亦死於陣中，鄧艾憐其忠將父子合葬。",
  "乘虛攻打綿竹，張遵、黃崇、李球三人殺出戰死，鄧艾因此得了綿竹。",
  "勞軍已畢，遂來取成都。"
 ],
 "鍾會": [
  "離劍閣二十五里下寨，諸葛緒自來伏罪。",
  "怒斥諸葛緒失守陰平橋頭及擅自進兵，欲斬之，因衛瓘勸阻及衆人力勸，改將諸葛緒用檻車載赴洛陽。",
  "將諸葛緒所領之兵收在部下調遣。",
  "接見鄧艾，帳前列武士數百人，鄧艾以言挑之提出取成都之計。",
  "大喜稱讚鄧艾此計甚妙，讓鄧艾引兵去，自己在此專候捷音。",
  "回本帳與諸將說鄧艾乃庸才，並解釋自己只以正道而行，何愁蜀地不破。",
  "置雲梯礮架，只打劍門關。",
  "聞報鄧艾要去取成都，笑其不智。"
 ],
 "黃皓": [
  "被後主召問鄧艾兵至之事，奏稱是詐傳，神人必不肯誤陛下。"
 ]
}